vulnlist/__init__.py
vulnlist/__main__.py
vulnlist/cli/__init__.py
vulnlist/cli/cli.py
vulnlist/cli/config.py
vulnlist/distribution.py
vulnlist/provider.py
vulnlist/providers/__init__.py
vulnlist/providers/alpine/__init__.py
vulnlist/providers/alpine/parser.py
vulnlist/providers/amazon/__init__.py
vulnlist/providers/amazon/parser.py
vulnlist/providers/chainguard/__init__.py
vulnlist/providers/debian/__init__.py
vulnlist/providers/debian/parser.py
vulnlist/providers/github/__init__.py
vulnlist/providers/github/parser.py
vulnlist/providers/mariner/DEVELOPING.md
vulnlist/providers/mariner/__init__.py
vulnlist/providers/mariner/generate_models.py
vulnlist/providers/mariner/model/__init__.py
vulnlist/providers/mariner/model/generated.py
vulnlist/providers/mariner/parser.py
vulnlist/providers/nvd/__init__.py
vulnlist/providers/nvd/api.py
vulnlist/providers/nvd/manager.py
vulnlist/providers/nvd/overrides.py
vulnlist/providers/oracle/__init__.py
vulnlist/providers/oracle/parser.py
vulnlist/providers/rhel/__init__.py
vulnlist/providers/rhel/oval_parser.py
vulnlist/providers/rhel/parser.py
vulnlist/providers/sles/__init__.py
vulnlist/providers/sles/parser.py
vulnlist/providers/ubuntu/__init__.py
vulnlist/providers/ubuntu/git.py
vulnlist/providers/ubuntu/parser.py
vulnlist/providers/wolfi/__init__.py
vulnlist/providers/wolfi/parser.py
vulnlist/result.py
vulnlist/schema.py
vulnlist/utils/__init__.py
vulnlist/utils/archive.py
vulnlist/utils/fdb.py
vulnlist/utils/hasher.py
vulnlist/utils/http.py
vulnlist/utils/oval_parser.py
vulnlist/utils/oval_v2.py
vulnlist/utils/rpm.py
vulnlist/utils/vulnerability.py
vulnlist/workspace.py
vulnlist-0.22.0.dist-info/LICENSE
vulnlist-0.22.0.dist-info/METADATA
vulnlist-0.22.0.dist-info/WHEEL
vulnlist-0.22.0.dist-info/entry_points.txt
vulnlist-0.22.0.dist-info/RECORD
