Metadata-Version: 2.1
Name: vulnlist
Version: 0.22.0
Summary: vulnlist ~= 'vulnerability data funnel'
Home-page: https://github.com/khulnasoft-lab/vulnlist
License: Apache-2.0
Keywords: vulnerability,data,aggregator,grype,vulnerability-data
Author: KhulnaSoft Security
Author-email: security@khulnasoft.com
Requires-Python: >=3.9,<4.0
Classifier: Development Status :: 5 - Production/Stable
Classifier: Intended Audience :: Developers
Classifier: Intended Audience :: Information Technology
Classifier: Intended Audience :: System Administrators
Classifier: License :: OSI Approved :: Apache Software License
Classifier: Natural Language :: English
Classifier: Operating System :: MacOS
Classifier: Operating System :: POSIX :: Linux
Classifier: Programming Language :: Python :: 3
Classifier: Programming Language :: Python :: 3.9
Classifier: Programming Language :: Python :: 3.10
Classifier: Programming Language :: Python :: 3.11
Classifier: Programming Language :: Python :: 3.12
Classifier: Topic :: Security
Classifier: Topic :: Software Development :: Libraries :: Python Modules
Classifier: Topic :: Utilities
Requires-Dist: PyYAML (>=6.0,<7.0)
Requires-Dist: SQLAlchemy (>=1.4.46,<2.0)
Requires-Dist: click (>=8.1.3,<9.0.0)
Requires-Dist: colorlog (>=6.7.0,<7.0.0)
Requires-Dist: cvss (>=2.6,<4.0)
Requires-Dist: defusedxml (>=0.7.1,<0.8.0)
Requires-Dist: ijson (>=2.5.1,<4.0)
Requires-Dist: importlib-metadata (>=7.0.1,<8.0.0)
Requires-Dist: iso8601 (>=2.1.0,<3.0.0)
Requires-Dist: mashumaro (>=3.10,<4.0)
Requires-Dist: mergedeep (>=1.3.4,<2.0.0)
Requires-Dist: orjson (>=3.8.6,<4.0.0)
Requires-Dist: pytest-snapshot (>=0.9.0,<0.10.0)
Requires-Dist: python-dateutil (>=2.8.2,<3.0.0)
Requires-Dist: requests (>=2.28.1,<3.0.0)
Requires-Dist: xsdata[cli,lxml,soap] (>=22.12,<25.0)
Requires-Dist: xxhash (>=3.1.0,<4.0.0)
Requires-Dist: zstandard (>=0.22.0,<0.23.0)
Project-URL: Repository, https://github.com/khulnasoft-lab/vulnlist
